{
  "id": "lissafi-local-env",
  "name": "LISSAFI-P — Local",
  "values": [
    {
      "key": "base_url",
      "value": "http://localhost:3000/api/v1",
      "type": "default",
      "enabled": true
    },
    {
      "key": "test_phone",
      "value": "+237699123456",
      "type": "default",
      "enabled": true,
      "description": "Numéro de téléphone de test — à changer si déjà utilisé en DB"
    },
    {
      "key": "test_password",
      "value": "1234",
      "type": "default",
      "enabled": true,
      "description": "Mot de passe 4 chiffres utilisé pour les tests"
    },
    {
      "key": "otp_code",
      "value": "",
      "type": "default",
      "enabled": true,
      "description": "⚠ À remplir manuellement après register — lire les logs du serveur (NODE_ENV=development)"
    },
    {
      "key": "userId",
      "value": "",
      "type": "default",
      "enabled": true,
      "description": "Auto-rempli par le test register"
    },
    {
      "key": "identifier",
      "value": "",
      "type": "default",
      "enabled": true,
      "description": "Auto-rempli par le test register (= test_phone)"
    },
    {
      "key": "access_token",
      "value": "",
      "type": "default",
      "enabled": true,
      "description": "Auto-rempli par login ou set-password"
    },
    {
      "key": "refresh_token",
      "value": "",
      "type": "default",
      "enabled": true,
      "description": "Auto-rempli par login ou set-password"
    }
  ],
  "_postman_variable_scope": "environment",
  "info": {
    "_postman_id": "lissafi-local-env-v1",
    "name": "LISSAFI-P — Local",
    "schema": "https://schema.getpostman.com/json/collection/v2.1.0/collection.json"
  }
}
